{
  "_template": "/page/list/PageList.hbs",
  "_styledTemplate": "/page/list/PageListH.hbs",
  "title": "List H",
  "pagination": [
    {
      "_template": "/link/Link.hbs",
      "body": "Previous Page",
      "href": ""
    },
    {
      "_template": "/link/Link.hbs",
      "body": "Next Page",
      "href": "#"
    }
  ],
  "items": [
    {
      "_include": "/page/promo/PagePromo.json"
    },
    {
      "_include": "/page/promo/PagePromo.json"
    },
    {
      "_include": "/page/promo/PagePromo.json"
    },
    {
      "_include": "/page/promo/PagePromo.json"
    },
    {
      "_include": "/page/promo/PagePromo.json"
    },
    {
      "_include": "/page/promo/PagePromo.json"
    }
  ]
}
